LICENSE.txt
README.rst
pyproject.toml
distogram/__init__.py
distogram.egg-info/PKG-INFO
distogram.egg-info/SOURCES.txt
distogram.egg-info/dependency_links.txt
distogram.egg-info/requires.txt
distogram.egg-info/top_level.txt
tests/test_bounds.py
tests/test_count.py
tests/test_count_at.py
tests/test_frequency_density_distribution.py
tests/test_histogram.py
tests/test_quantile.py
tests/test_stats.py
tests/test_update.py