Metadata-Version: 2.2
Name: distogram
Version: 3.0.3
Summary: A library to compute histograms on distributed environments, on streaming data
Author: Romain Picard
Author-email: romain.picard@oakbits.com
License: Copyright (c) 2020 by Romain Picard
Project-URL: repository, https://github.com/maki-nage/distogram.git
Keywords: reactivex,streaming,data-science
Classifier: Development Status :: 5 - Production/Stable
Classifier: License :: OSI Approved :: MIT License
Classifier: Intended Audience :: Developers
Classifier: Programming Language :: Python :: 3
Classifier: Topic :: Scientific/Engineering :: Mathematics
Requires-Python: >=3.6
License-File: LICENSE.txt
Provides-Extra: test
Requires-Dist: pytest; extra == "test"
